README.md
setup.py
pulumi_readarr/__init__.py
pulumi_readarr/_utilities.py
pulumi_readarr/provider.py
pulumi_readarr/pulumi-plugin.json
pulumi_readarr/py.typed
pulumi_readarr.egg-info/PKG-INFO
pulumi_readarr.egg-info/SOURCES.txt
pulumi_readarr.egg-info/dependency_links.txt
pulumi_readarr.egg-info/not-zip-safe
pulumi_readarr.egg-info/requires.txt
pulumi_readarr.egg-info/top_level.txt
pulumi_readarr/authors/__init__.py
pulumi_readarr/authors/author.py
pulumi_readarr/authors/get_author.py
pulumi_readarr/authors/get_authors.py
pulumi_readarr/authors/outputs.py
pulumi_readarr/config/__init__.py
pulumi_readarr/config/vars.py
pulumi_readarr/downloadclients/__init__.py
pulumi_readarr/downloadclients/aria2.py
pulumi_readarr/downloadclients/config.py
pulumi_readarr/downloadclients/deluge.py
pulumi_readarr/downloadclients/download_client.py
pulumi_readarr/downloadclients/flood.py
pulumi_readarr/downloadclients/get_config.py
pulumi_readarr/downloadclients/get_download_client.py
pulumi_readarr/downloadclients/get_download_clients.py
pulumi_readarr/downloadclients/get_remote_path_mapping.py
pulumi_readarr/downloadclients/get_remote_path_mappings.py
pulumi_readarr/downloadclients/hadouken.py
pulumi_readarr/downloadclients/nzbget.py
pulumi_readarr/downloadclients/nzbvortex.py
pulumi_readarr/downloadclients/outputs.py
pulumi_readarr/downloadclients/pneumatic.py
pulumi_readarr/downloadclients/qbittorrent.py
pulumi_readarr/downloadclients/remote_path_mapping.py
pulumi_readarr/downloadclients/rtorrent.py
pulumi_readarr/downloadclients/sabnzbd.py
pulumi_readarr/downloadclients/torrent_blackhole.py
pulumi_readarr/downloadclients/torrent_download_station.py
pulumi_readarr/downloadclients/transmission.py
pulumi_readarr/downloadclients/usenet_blackhole.py
pulumi_readarr/downloadclients/usenet_download_station.py
pulumi_readarr/downloadclients/utorrent.py
pulumi_readarr/downloadclients/vuze.py
pulumi_readarr/importlists/__init__.py
pulumi_readarr/importlists/exclusion.py
pulumi_readarr/importlists/get_exclusion.py
pulumi_readarr/importlists/get_exclusions.py
pulumi_readarr/importlists/get_import_list.py
pulumi_readarr/importlists/get_import_lists.py
pulumi_readarr/importlists/goodreads_bookshelf.py
