Metadata-Version: 2.1
Name: pulumi-readarr
Version: 3.0.0a2
Summary: A Pulumi package for creating and managing Readarr resources
Home-page: https://github.com/MaienM/pulumi-readarr
License: Apache-2.0
Project-URL: Repository, https://github.com/MaienM/pulumi-readarr
Keywords: pulumi readarr category/utility
Requires-Python: >=3.7
